velait/__init__.py
velait/main/__init__.py
velait/main/apps.py
velait/main/exceptions.py
velait/main/logging.py
velait/main/middleware.py
velait/main/models.py
velait/main/parser.py
velait/main/render.py
velait/main/settings.py
velait/main/signals.py
velait/main/utils.py
velait/main/api/__init__.py
velait/main/api/exception_handlers.py
velait/main/api/pagination.py
velait/main/api/responses.py
velait/main/api/serializers.py
velait/main/api/views.py
velait/main/migrations/__init__.py
velait/main/services/__init__.py
velait/main/services/utils.py
velait/main/services/search/__init__.py
velait/main/services/search/base_search.py
velait/main/services/search/search.py
velait/velait_users/__init__.py
velait/velait_users/apps.py
velait/velait_users/exceptions.py
velait/velait_users/middleware.py
velait/velait_users/services.py
velait/velait_users/urls.py
velait/velait_users/views.py
velait/velait_users/api/__init__.py
velait/velait_users/api/serializers.py
velait/velait_users/api/views.py
velait/velait_users/migrations/__init__.py
velait_api-0.5.4.dist-info/METADATA
velait_api-0.5.4.dist-info/WHEEL
velait_api-0.5.4.dist-info/top_level.txt
velait_api-0.5.4.dist-info/RECORD
